pytest_notifier/__init__.py
pytest_notifier/notifier.py
pytest_notifier/test_notifier.py
pytest_notifier/test_utils.py
pytest_notifier/utils.py
pytest_notifier-1.0.4.dist-info/METADATA
pytest_notifier-1.0.4.dist-info/WHEEL
pytest_notifier-1.0.4.dist-info/entry_points.txt
pytest_notifier-1.0.4.dist-info/top_level.txt
pytest_notifier-1.0.4.dist-info/RECORD
