Metadata-Version: 2.1
Name: pytest-notifier
Version: 1.0.4
Summary: A pytest plugin to notify test result
Home-page: https://github.com/ratson/pytest-notifier
Author: Ratson
Author-email: contact@ratson.name
License: UNKNOWN
Keywords: pytest,pytest-,osx,linux,notifications,notifier,notificationcenter,py.test,terminal-notifier,libnotify
Platform: UNKNOWN
Classifier: Development Status :: 3 - Alpha
Classifier: Intended Audience :: Developers
Classifier: License :: OSI Approved :: MIT License
Classifier: Programming Language :: Python
Classifier: Programming Language :: Python :: 2
Classifier: Programming Language :: Python :: 2.7
Classifier: Programming Language :: Python :: 3
Classifier: Programming Language :: Python :: 3.4
Classifier: Programming Language :: Python :: 3.5
Classifier: Programming Language :: Python :: 3.6
Classifier: Programming Language :: Python :: 3.7
Requires-Dist: pytest
